json_schema_filter/__init__.py
json_schema_filter/filter.py
json_schema_filter/filter_validator/__init__.py
json_schema_filter/filter_validator/equals_validator.py
json_schema_filter/filter_validator/iequal_validator.py
json_schema_filter/filter_validator/nequals_validator.py
json_schema_filter/filter_validator/registry.py
json_schema_filter/logging.py
json_schema_filter/struct/__init__.py
json_schema_filter/struct/filtered.py
json_schema_filter-0.3.0.dist-info/LICENSE
json_schema_filter-0.3.0.dist-info/METADATA
json_schema_filter-0.3.0.dist-info/WHEEL
json_schema_filter-0.3.0.dist-info/RECORD
