Metadata-Version: 2.1
Name: json-schema-filter
Version: 0.3.0
Summary: A library that uses json schema to filter the objects
Home-page: https://github.com/Bharat23/json-schema-filter
License: MIT
Author: Bharat Sinha
Author-email: bharat.sinha.2307@gmail.com
Requires-Python: >=3.10,<4.0
Classifier: License :: OSI Approved :: MIT License
Classifier: Programming Language :: Python :: 3
Classifier: Programming Language :: Python :: 3.10
Classifier: Programming Language :: Python :: 3.11
Classifier: Programming Language :: Python :: 3.12
Requires-Dist: jsonschema (>=4.20.0,<5.0.0)
Requires-Dist: pyyaml (>=6.0.1,<7.0.0)
Project-URL: Repository, https://github.com/Bharat23/json-schema-filter
